askelerator/__init__.py
askelerator/actions.py
askelerator/cli.py
askelerator/generator.py
askelerator/helpers.py
askelerator-0.0.3.dist-info/LICENSE
askelerator-0.0.3.dist-info/METADATA
askelerator-0.0.3.dist-info/WHEEL
askelerator-0.0.3.dist-info/entry_points.txt
askelerator-0.0.3.dist-info/top_level.txt
askelerator-0.0.3.dist-info/RECORD
