Metadata-Version: 2.1
Name: askelerator
Version: 0.0.3
Summary: A code skeleton generator for accelerated coding.
Home-page: https://askelerator.pw
Author: lfx
Author-email: fx@zrkf.pw
License: UNKNOWN
Platform: UNKNOWN
Classifier: Programming Language :: Python :: 3
Classifier: License :: OSI Approved :: GNU General Public License v3 (GPLv3)
Classifier: Operating System :: OS Independent
